gort/__init__.py
gort/__main__.py
gort/enums.py
gort/exceptions.py
gort/exposure.py
gort/gort.py
gort/observer.py
gort/pointing.py
gort/remote.py
gort/tile.py
gort/tools.py
gort/transforms.py
gort/devices/__init__.py
gort/devices/ag.py
gort/devices/core.py
gort/devices/enclosure.py
gort/devices/guider.py
gort/devices/nps.py
gort/devices/spec.py
gort/devices/telemetry.py
gort/devices/telescope.py
gort/etc/actor_schema.json
gort/etc/calibrations.yaml
gort/etc/lvmgort.yml
gort/overwatcher/__init__.py
gort/overwatcher/alerts.py
gort/overwatcher/calibrations.py
gort/overwatcher/core.py
gort/overwatcher/ephemeris.py
gort/overwatcher/events.py
gort/overwatcher/health.py
gort/overwatcher/observer.py
gort/overwatcher/overwatcher.py
gort/overwatcher/safety.py
gort/overwatcher/transparency.py
gort/overwatcher/actor/__init__.py
gort/overwatcher/actor/actor.py
gort/overwatcher/actor/commands.py
gort/overwatcher/helpers/__init__.py
gort/overwatcher/helpers/dome.py
gort/overwatcher/helpers/health.py
gort/overwatcher/helpers/notifier.py
gort/overwatcher/helpers/tasks.py
gort/overwatcher/troubleshooter/__init__.py
gort/overwatcher/troubleshooter/recipes.py
gort/overwatcher/troubleshooter/troubleshooter.py
gort/recipes/__init__.py
gort/recipes/base.py
gort/recipes/calibrations.py
gort/recipes/operations.py
gort/recipes/test.py
lvmgort-1.11.5.dist-info/METADATA
lvmgort-1.11.5.dist-info/WHEEL
lvmgort-1.11.5.dist-info/entry_points.txt
lvmgort-1.11.5.dist-info/licenses/LICENSE.md
lvmgort-1.11.5.dist-info/RECORD
