Metadata-Version: 2.4
Name: lvmgort
Version: 1.11.5
Summary: The brains of LVM observing
Project-URL: Homepage, https://github.com/sdss/lvmgort
Project-URL: Repository, https://github.com/sdss/lvmgort
Project-URL: Documentation, https://lvmgort.readthedocs.org
Author-email: José Sánchez-Gallego <gallegoj@uw.edu>
License: BSD-3-Clause
License-File: LICENSE.md
Requires-Python: <4,>=3.10
Requires-Dist: astropy>=6.0.0; python_version < '3.11'
Requires-Dist: astropy>=7.0.0; python_version >= '3.11'
Requires-Dist: httpx>=0.27.0
Requires-Dist: lvmopstools>=0.5.20
Requires-Dist: peewee>=3.16.2
Requires-Dist: polars>=1.0.0
Requires-Dist: psycopg2-binary>=2.9.6
Requires-Dist: pydantic>=2.9.2
Requires-Dist: redis[hiredis]>=5.0.3
Requires-Dist: rich>=13.4.2
Requires-Dist: sdss-clu>=2.5.3
Requires-Dist: sdsstools>=1.8.1
Requires-Dist: typer>=0.15.2
Requires-Dist: unclick>=0.1.0
